{"id":27750,"path":".\\Library\\PackageCache\\com.unity.render-pipelines.core@14.0.12\\Runtime\\Debugging\\Prefabs\\Widgets\\DebugUIMessageBox.prefab","assetBundleId":-1,"components":[{"type":16,"id":27584,"data":[0.5,0.5,0,0,0,0,590,0,295,0,0,0,0,0,1,1,1,1]},{"type":10,"id":28168,"enabled":1,"class":24,"data":[0,1,1,1,1,0,0,0,6,6,4,4,0]},{"type":10,"id":28170,"enabled":1,"class":25,"data":[0,2]},{"type":4,"id":28172,"enabled":1,"class":61,"data":[28,28880,0.800000011920929,0.800000011920929,0.800000011920929,1,0.25,0.649999976158142,0.800000011920929,1]},{"type":21,"id":28174,"data":[1]},{"type":10,"id":28176,"enabled":1,"class":22,"data":[null,null,1,0,1,4,1,1,0,0,1,null,null,1,1,1,1,0.270588248968124,1,0,0,0,0]}],"children":[{"id":28178,"path":".\\Library\\PackageCache\\com.unity.render-pipelines.core@14.0.12\\Runtime\\Debugging\\Prefabs\\Widgets\\DebugUIMessageBox.prefab","assetBundleId":-1,"components":[{"type":16,"id":27752,"data":[0.5,0.5,0,0,0,0,0,0,0,0,0,0,0,0,1,1,1,1]},{"type":21,"id":28878,"data":[1]},{"type":10,"id":28880,"enabled":1,"class":28,"data":[[32,28994,15,0,0,1,40,3,0,0,0,1,1],"Message text\n",null,null,1,0.800000011920929,0.800000011920929,0.800000011920929,1,1,0,0,0,0]}],"children":[],"data":["Text",0,1,0,5]}],"data":["DebugUIMessageBox",0,1,0,0]}